molo.forms-11.3.4-py3.8-nspkg.pth
molo/forms/__init__.py
molo/forms/adapters.py
molo/forms/admin.py
molo/forms/admin_urls.py
molo/forms/blocks.py
molo/forms/edit_handlers.py
molo/forms/forms.py
molo/forms/models.py
molo/forms/rules.py
molo/forms/serializers.py
molo/forms/urls.py
molo/forms/utils.py
molo/forms/views.py
molo/forms/wagtail_hooks.py
molo/forms/widgets.py
molo/forms/migrations/0001_initial.py
molo/forms/migrations/0002_create_forms_index_page.py
molo/forms/migrations/0003_rename_molo_form.py
molo/forms/migrations/0004_add_email_form.py
molo/forms/migrations/0005_rename_rules_class_name.py
molo/forms/migrations/0006_moloformpage_contact_form.py
molo/forms/migrations/0007_alter_field_type.py
molo/forms/migrations/0008_articlepageforms.py
molo/forms/migrations/0009_add_article_form_field.py
molo/forms/migrations/0010_save_article_object.py
molo/forms/migrations/0011_auto_20210111_1714.py
molo/forms/migrations/0012_auto_20210511_2216.py
molo/forms/migrations/__init__.py
molo/forms/static/css/blocks/skiplogic.css
molo/forms/static/js/form-admin.js
molo/forms/static/js/blocks/skiplogic.js
molo/forms/static/js/blocks/skiplogic_stream.js
molo/forms/static/js/widgets/character_count.js
molo/forms/templates/csv_group_creation/create.html
molo/forms/templates/forms/forms_headline.html
molo/forms/templates/forms/forms_list.html
molo/forms/templates/forms/molo_form_page.html
molo/forms/templates/forms/molo_form_page_success.html
molo/forms/templates/modeladmin/create.html
molo/forms/templates/wagtailadmin/edit_handlers/inline_panel.html
molo/forms/templates/wagtailadmin/shared/field.html
molo/forms/templates/wagtailforms/index_submissions.html
molo/forms/templates/wagtailforms/list_submissions.html
molo/forms/templatetags/__init__.py
molo/forms/templatetags/forms_personalise_extras.py
molo/forms/templatetags/molo_forms_tags.py
molo/forms/test_templates/article_page.html
molo/forms/test_templates/base.html
molo/forms/test_templates/main.html
molo.forms-11.3.4.dist-info/LICENSE
molo.forms-11.3.4.dist-info/METADATA
molo.forms-11.3.4.dist-info/WHEEL
molo.forms-11.3.4.dist-info/namespace_packages.txt
molo.forms-11.3.4.dist-info/top_level.txt
molo.forms-11.3.4.dist-info/RECORD
