Metadata-Version: 2.1
Name: molo.forms
Version: 11.3.4
Summary: A form builder for Molo applications.
Home-page: https://github.com/praekelt/molo.forms
Author: Praekelt.org
Author-email: dev@praekelt.org
License: BSD
Keywords: molo.forms
Platform: UNKNOWN
Classifier: Intended Audience :: Developers
Classifier: Natural Language :: English
Classifier: Programming Language :: Python :: 3.6
License-File: LICENSE
Requires-Dist: molo.core (<12.0.0,>=11.0.7)
Requires-Dist: celery (<5.0,>4.0)
Requires-Dist: dateparser (<0.8.0,>=0.7.0)
Requires-Dist: wagtail-personalisation-molo (==3.0.4)
Requires-Dist: psycopg2-binary
Requires-Dist: psycopg2
Requires-Dist: html5lib (==0.9999999)
Requires-Dist: six (==1.12.0)
Requires-Dist: Unidecode (==0.04.16)
